basename/__init__.py
basename/main.py
pnu_basename-1.2.1.data/data/man/man1/basename.1.gz
pnu_basename-1.2.1.data/data/man/man1/dirname.1.gz
pnu_basename-1.2.1.dist-info/License
pnu_basename-1.2.1.dist-info/METADATA
pnu_basename-1.2.1.dist-info/WHEEL
pnu_basename-1.2.1.dist-info/entry_points.txt
pnu_basename-1.2.1.dist-info/top_level.txt
pnu_basename-1.2.1.dist-info/RECORD
