Metadata-Version: 2.1
Name: pnu-basename
Version: 1.2.1
Summary: return filename or directory portion of pathname
Home-page: https://github.com/HubTou/basename/
Author: HubTou
Author-email: nobody@nowhere.invalid
License: BSD 3-Clause License
Project-URL: Bug Tracker, https://github.com/HubTou/basename/issues
Keywords: pnu-project
Platform: UNKNOWN
Classifier: Development Status :: 5 - Production/Stable
Classifier: Environment :: Console
Classifier: Intended Audience :: Developers
Classifier: Intended Audience :: End Users/Desktop
Classifier: License :: OSI Approved :: BSD License
Classifier: Natural Language :: English
Classifier: Operating System :: OS Independent
Classifier: Operating System :: POSIX :: BSD :: FreeBSD
Classifier: Operating System :: Microsoft :: Windows
Classifier: Programming Language :: Python :: 3
Classifier: Programming Language :: Python :: 3.0
Classifier: Programming Language :: Python :: 3.1
Classifier: Programming Language :: Python :: 3.2
Classifier: Programming Language :: Python :: 3.3
Classifier: Programming Language :: Python :: 3.4
Classifier: Programming Language :: Python :: 3.5
Classifier: Programming Language :: Python :: 3.6
Classifier: Programming Language :: Python :: 3.7
Classifier: Programming Language :: Python :: 3.8
Classifier: Programming Language :: Python :: 3.9
Classifier: Programming Language :: Python :: 3.10
Classifier: Topic :: Software Development
Classifier: Topic :: System
Classifier: Topic :: Text Processing
Classifier: Topic :: Utilities
Requires-Python: >=3.0
License-File: License
